ne_spectrum/__init__.py
ne_spectrum/spectra.py
ne_spectrum-0.1.1.dist-info/LICENSE
ne_spectrum-0.1.1.dist-info/METADATA
ne_spectrum-0.1.1.dist-info/WHEEL
ne_spectrum-0.1.1.dist-info/top_level.txt
ne_spectrum-0.1.1.dist-info/RECORD
