Metadata-Version: 2.1
Name: ne-spectrum
Version: 0.1.1
Summary: Neighbor embedding spectrum
Author-email: Manuel Klockow <manuel.klockow@stud.uni-heidelberg.de>, Sebastian Damrich <sebastian.damrich@uni-tuebingen.de>
License: MIT
Project-URL: homepage, https://github.com/sciai-lab/tsne-slider
Classifier: Programming Language :: Python :: 3
Requires-Python: >=3.12
License-File: LICENSE
Requires-Dist: numpy
Requires-Dist: openTSNE
Requires-Dist: contrastive-ne >=0.3.8
Requires-Dist: matplotlib
Requires-Dist: pillow
